__init__.py
npycli/__init__.py
npycli/ansi.py
npycli/cli.py
npycli/command.py
npycli/errors.py
npycli/kwarg_alasing.py
npycli/kwarg_aliasing.py
npycli/parameters.py
npycli/parsing.py
npycli-0.3.0.dist-info/licenses/LICENSE
npycli-0.3.0.dist-info/METADATA
npycli-0.3.0.dist-info/WHEEL
npycli-0.3.0.dist-info/top_level.txt
npycli-0.3.0.dist-info/RECORD
