Metadata-Version: 2.4
Name: npycli
Version: 0.3.0
Summary: CLI program helper/framework
Author-email: Franklyn Vasquez <franklynvasquez24@gmail.com>
Project-URL: Repository, https://github.com/Narwhalsss360/npycli
Project-URL: Issues, https://github.com/Narwhalsss360/npycli/issues
Keywords: cli,npy,command line interface
Classifier: Programming Language :: Python :: 3
License-File: LICENSE
Dynamic: license-file
